Multiplexers/MUX2x1.v
module MUX2x1(input in0, in1, sel,
    output out);
    assign out = (sel == 0)? in0: in1;
endmodule

Multiplexers/tb_MUX2x1.v
`timescale 1ns/1ps

module tb_MUX2x1;
    wire out;
    reg in0;
    reg in1;
    reg sel;

    MUX2x1 uut(
        .out(out),
        .in0(in0),
        .in1(in1),
        .sel(sel)
    );

    initial begin
        $dumpfile("2x1MUXwaveform.vcd");
        $dumpvars(0, tb_MUX2x1);

        sel = 0; in0 = 0; in1 = 0; #10;
        $display("input_1 = %b, input_2 = %b, select_line = %b, output = %b", in0, in1, sel, out);
        sel = 0; in0 = 0; in1 = 1; #10;
        $display("input_1 = %b, input_2 = %b, select_line = %b, output = %b", in0, in1, sel, out);
        sel = 0; in0 = 1; in1 = 0; #10;
        $display("input_1 = %b, input_2 = %b, select_line = %b, output = %b", in0, in1, sel, out);
        sel = 0; in0 = 1; in1 = 1; #10;
        $display("input_1 = %b, input_2 = %b, select_line = %b, output = %b", in0, in1, sel, out);
        sel = 1; in0 = 0; in1 = 0; #10;
        $display("input_1 = %b, input_2 = %b, select_line = %b, output = %b", in0, in1, sel, out);
        sel = 1; in0 = 0; in1 = 1; #10;
        $display("input_1 = %b, input_2 = %b, select_line = %b, output = %b", in0, in1, sel, out);
        sel = 1; in0 = 1; in1 = 0; #10;
        $display("input_1 = %b, input_2 = %b, select_line = %b, output = %b", in0, in1, sel, out);
        sel = 1; in0 = 1; in1 = 1; #10;
        $display("input_1 = %b, input_2 = %b, select_line = %b, output = %b", in0, in1, sel, out);

        $finish;
    end
endmodule

2x1MUXwaveform.vcd
$date
	Mon Jun 30 14:59:48 2025
$end
$version
	Icarus Verilog
$end
$timescale
	1ps
$end
$scope module tb_MUX2x1 $end
$var wire 1 ! out $end
$var reg 1 " in0 $end
$var reg 1 # in1 $end
$var reg 1 $ sel $end
$scope module uut $end
$var wire 1 " in0 $end
$var wire 1 # in1 $end
$var wire 1 $ sel $end
$var wire 1 ! out $end
$upscope $end
$upscope $end
$enddefinitions $end
$comment Show the parameter values. $end
$dumpall
$end
#0
$dumpvars
0$
0#
0"
0!
$end
#10000
1#
#20000
1!
0#
1"
#30000
1#
#40000
0!
0#
0"
1$
#50000
1!
1#
#60000
0!
0#
1"
#70000
1!
1#
