Multiplexers/MUX4x1.v
module MUX4x1 (
    input in0, in1, in2, in3,
    input [1:0]sel,
    output reg out); //output inside always block must always be declared as a register

    always @(*)
        begin
            case(sel)
                2'b00: out = in0;
                2'b01: out = in1;
                2'b10: out = in2;
                2'b11: out = in3;
            endcase
        end
endmodule

Multiplexers/tb_MUX4x1.v
`timescale 1ns/1ps

module tb_MUX4x1;
    reg in0;
    reg in1;
    reg in2;
    reg in3;
    reg [3:0]inputs;
    reg [1:0]sel;
    wire out;
    integer i;

    MUX4x1 uut(
        .in0(in0),
        .in1(in1),
        .in2(in2),
        .in3(in3),
        .sel(sel),
        .out(out)
    );

    initial begin
        $dumpfile("4x1MUXwaveform.vcd");
        $dumpvars(0, tb_MUX4x1);

        for(i = 0; i < 16; i = i + 1) begin
            inputs = i[3:0];
            in0 = inputs[0];
            in1 = inputs[1];
            in2 = inputs[2];
            in3 = inputs[3];

            sel = 2'b00; #10;
            $display("sel = %b, inputs = %b, out = %b", sel, inputs, out);
            sel = 2'b01; #10;
            $display("sel = %b, inputs = %b, out = %b", sel, inputs, out);
            sel = 2'b10; #10;
            $display("sel = %b, inputs = %b, out = %b", sel, inputs, out);
            sel = 2'b11; #10;
            $display("sel = %b, inputs = %b, out = %b", sel, inputs, out);
        end
        $finish;
    end
endmodule

4x1MUXwaveform.vcd
$date
	Mon Jun 30 16:03:41 2025
$end
$version
	Icarus Verilog
$end
$timescale
	1ps
$end
$scope module tb_MUX4x1 $end
$var wire 1 ! out $end
$var reg 1 " in0 $end
$var reg 1 # in1 $end
$var reg 1 $ in2 $end
$var reg 1 % in3 $end
$var reg 4 & inputs [3:0] $end
$var reg 2 ' sel [1:0] $end
$var integer 32 ( i [31:0] $end
$scope module uut $end
$var wire 1 " in0 $end
$var wire 1 # in1 $end
$var wire 1 $ in2 $end
$var wire 1 % in3 $end
$var wire 2 ) sel [1:0] $end
$var reg 1 ! out $end
$upscope $end
$upscope $end
$enddefinitions $end
$comment Show the parameter values. $end
$dumpall
$end
#0
$dumpvars
b0 )
b0 (
b0 '
b0 &
0%
0$
0#
0"
0!
$end
#10000
b1 '
b1 )
#20000
b10 '
b10 )
#30000
b11 '
b11 )
#40000
1!
b0 '
b0 )
1"
b1 &
b1 (
#50000
0!
b1 '
b1 )
#60000
b10 '
b10 )
#70000
b11 '
b11 )
#80000
b0 '
b0 )
1#
0"
b10 &
b10 (
#90000
1!
b1 '
b1 )
#100000
0!
b10 '
b10 )
#110000
b11 '
b11 )
#120000
1!
b0 '
b0 )
1"
b11 &
b11 (
#130000
b1 '
b1 )
#140000
0!
b10 '
b10 )
#150000
b11 '
b11 )
#160000
b0 '
b0 )
1$
0#
0"
b100 &
b100 (
#170000
b1 '
b1 )
#180000
1!
b10 '
b10 )
#190000
0!
b11 '
b11 )
#200000
1!
b0 '
b0 )
1"
b101 &
b101 (
#210000
0!
b1 '
b1 )
#220000
1!
b10 '
b10 )
#230000
0!
b11 '
b11 )
#240000
b0 '
b0 )
1#
0"
b110 &
b110 (
#250000
1!
b1 '
b1 )
#260000
b10 '
b10 )
#270000
0!
b11 '
b11 )
#280000
1!
b0 '
b0 )
1"
b111 &
b111 (
#290000
b1 '
b1 )
#300000
b10 '
b10 )
#310000
0!
b11 '
b11 )
#320000
b0 '
b0 )
1%
0$
0#
0"
b1000 &
b1000 (
#330000
b1 '
b1 )
#340000
b10 '
b10 )
#350000
1!
b11 '
b11 )
#360000
b0 '
b0 )
1"
b1001 &
b1001 (
#370000
0!
b1 '
b1 )
#380000
b10 '
b10 )
#390000
1!
b11 '
b11 )
#400000
0!
b0 '
b0 )
1#
0"
b1010 &
b1010 (
#410000
1!
b1 '
b1 )
#420000
0!
b10 '
b10 )
#430000
1!
b11 '
b11 )
#440000
b0 '
b0 )
1"
b1011 &
b1011 (
#450000
b1 '
b1 )
#460000
0!
b10 '
b10 )
#470000
1!
b11 '
b11 )
#480000
0!
b0 '
b0 )
1$
0#
0"
b1100 &
b1100 (
#490000
b1 '
b1 )
#500000
1!
b10 '
b10 )
#510000
b11 '
b11 )
#520000
b0 '
b0 )
1"
b1101 &
b1101 (
#530000
0!
b1 '
b1 )
#540000
1!
b10 '
b10 )
#550000
b11 '
b11 )
#560000
0!
b0 '
b0 )
1#
0"
b1110 &
b1110 (
#570000
1!
b1 '
b1 )
#580000
b10 '
b10 )
#590000
b11 '
b11 )
#600000
b0 '
b0 )
1"
b1111 &
b1111 (
#610000
b1 '
b1 )
#620000
b10 '
b10 )
#630000
b11 '
b11 )
#640000
b10000 (
