Comparators/Comparator4bit.v
module Comparator4bit(
    input [3:0]in0,
    input [3:0]in1,
    output [3:0]greater,
    output [3:0]smaller,
    output [3:0]equal
    );

    assign greater = (in1 > in0);
    assign smaller = (in1 < in0);
    assign equal = (in1 == in0);

endmodule

Comparators/tb_Comparator4bit.v
`timescale 1ns/1ps

module tb_Comparator4bit();
    reg [3:0]in0;
    reg [3:0]in1;
    wire [3:0]greater;
    wire [3:0]smaller;
    wire [3:0]equal;

    Comparator4bit uut(
        .in0(in0),
        .in1(in1),
        .greater(greater),
        .smaller(smaller),
        .equal(equal)
    );

    initial begin
        $dumpfile("comparactorwaveform.vcd");
        $dumpvars(0, tb_Comparator4bit);

        in0 = 4'b0000; in1 = 4'b0000; #10;
        $display("input1 = %b input0 = %b | Greater: %b | Smaller: %b | Equal: %b |", in1, in0, greater[0], smaller[0], equal[0]);
        in0 = 4'b1000; in1 = 4'b0000; #10;
        $display("input1 = %b input0 = %b | Greater: %b | Smaller: %b | Equal: %b |", in1, in0, greater[0], smaller[0], equal[0]);
        in0 = 4'b0000; in1 = 4'b1000; #10;
        $display("input1 = %b input0 = %b | Greater: %b | Smaller: %b | Equal: %b |", in1, in0, greater[0], smaller[0], equal[0]);
        in0 = 4'b1111; in1 = 4'b1111; #10;
        $display("input1 = %b input0 = %b | Greater: %b | Smaller: %b | Equal: %b |", in1, in0, greater[0], smaller[0], equal[0]);
        in0 = 4'b1110; in1 = 4'b0111; #10;
        $display("input1 = %b input0 = %b | Greater: %b | Smaller: %b | Equal: %b |", in1, in0, greater[0], smaller[0], equal[0]);
        in0 = 4'b0001; in1 = 4'b0000; #10;
        $display("input1 = %b input0 = %b | Greater: %b | Smaller: %b | Equal: %b |", in1, in0, greater[0], smaller[0], equal[0]);
        in0 = 4'b0000; in1 = 4'b0001; #10;
        $display("input1 = %b input0 = %b | Greater: %b | Smaller: %b | Equal: %b |", in1, in0, greater[0], smaller[0], equal[0]);
        in0 = 4'b0001; in1 = 4'b1000; #10;
        $display("input1 = %b input0 = %b | Greater: %b | Smaller: %b | Equal: %b |", in1, in0, greater[0], smaller[0], equal[0]);
        in0 = 4'b1000; in1 = 4'b0001; #10;
        $display("input1 = %b input0 = %b | Greater: %b | Smaller: %b | Equal: %b |", in1, in0, greater[0], smaller[0], equal[0]);
        in0 = 4'b0000; in1 = 4'b1111; #10;
        $display("input1 = %b input0 = %b | Greater: %b | Smaller: %b | Equal: %b |", in1, in0, greater[0], smaller[0], equal[0]);
        in0 = 4'b1111; in1 = 4'b1111; #10;
        $display("input1 = %b input0 = %b | Greater: %b | Smaller: %b | Equal: %b |", in1, in0, greater[0], smaller[0], equal[0]);

        $finish;
    end
endmodule

comparactorwaveform.vcd
$date
	Wed Jul 02 18:08:26 2025
$end
$version
	Icarus Verilog
$end
$timescale
	1ps
$end
$scope module tb_Comparator4bit $end
$var wire 4 ! smaller [3:0] $end
$var wire 4 " greater [3:0] $end
$var wire 4 # equal [3:0] $end
$var reg 4 $ in0 [3:0] $end
$var reg 4 % in1 [3:0] $end
$scope module uut $end
$var wire 4 & in0 [3:0] $end
$var wire 4 ' in1 [3:0] $end
$var wire 4 ( smaller [3:0] $end
$var wire 4 ) greater [3:0] $end
$var wire 4 * equal [3:0] $end
$upscope $end
$upscope $end
$enddefinitions $end
$comment Show the parameter values. $end
$dumpall
$end
#0
$dumpvars
b1 *
b0 )
b0 (
b0 '
b0 &
b0 %
b0 $
b1 #
b0 "
b0 !
$end
#10000
b1 !
b1 (
b0 #
b0 *
b1000 $
b1000 &
#20000
b1 "
b1 )
b1000 %
b1000 '
b0 !
b0 (
b0 #
b0 *
b0 $
b0 &
#30000
b1 #
b1 *
b1111 %
b1111 '
b0 "
b0 )
b0 !
b0 (
b1111 $
b1111 &
#40000
b1 !
b1 (
b111 %
b111 '
b0 "
b0 )
b0 #
b0 *
b1110 $
b1110 &
#50000
b0 %
b0 '
b0 "
b0 )
b1 !
b1 (
b1 $
b1 &
#60000
b1 "
b1 )
b1 %
b1 '
b0 !
b0 (
b0 #
b0 *
b0 $
b0 &
#70000
b1000 %
b1000 '
b1 "
b1 )
b0 #
b0 *
b1 $
b1 &
#80000
b1 !
b1 (
b1 %
b1 '
b0 "
b0 )
b0 #
b0 *
b1000 $
b1000 &
#90000
b1111 %
b1111 '
b1 "
b1 )
b0 !
b0 (
b0 $
b0 &
#100000
b0 "
b0 )
b1 #
b1 *
b1111 $
b1111 &
