EncodersDecoders/Decoder3x8.v
module Decoder3x8(
    input [2:0]in,
    input en,
    output reg [7:0]out
    );
    //My initial implementation
    /*assign out[0] = (~in[2]) & (~in[1]) & (~in[0]);
    assign out[1] = (~in[2]) & (~in[1]) & (in[0]);
    assign out[2] = (~in[2]) & (in[1]) & (~in[0]);
    assign out[3] = (~in[2]) & (in[1]) & (in[0]);
    assign out[4] = (in[2]) & (~in[1]) & (~in[0]);
    assign out[5] = (in[2]) & (~in[1]) & (in[0]);
    assign out[6] = (in[2]) & (in[1]) & (~in[0]);
    assign out[7] = (in[2]) & (in[1]) & (in[0]);*/

    //Implementation after learning about vectors:
    //assign out = 1 << in;

    //Implementation after learning about always blocks:
    always @(*) begin
        if (en)
            out = 1 << in;
        else
            out = 8'b00000000;
    end

endmodule

EncodersDecoders/tb_Decoder3x8.v
`timescale 1ns/1ps

module tb_Decoder3x8();
    reg [2:0]in;
    reg en;
    wire [7:0]out;

    Decoder3x8 uut(
        .in(in),
        .out(out),
        .en(en)
    );

    initial begin
        $dumpfile("decoder3x8waveform.vcd");
        $dumpvars(0, tb_Decoder3x8);

        in[2] = 0; in[1] = 0; in[0] = 0; en = 0; #10;
        $display("Enable = %b | input = %b | output = %b", en, in, out);
        in[2] = 0; in[1] = 0; in[0] = 0; en = 1; #10;
        $display("Enable = %b | input = %b | output = %b", en, in, out);
        in[2] = 0; in[1] = 0; in[0] = 1; en = 1; #10;
        $display("Enable = %b | input = %b | output = %b", en, in, out);
        in[2] = 0; in[1] = 1; in[0] = 0; en = 1; #10;
        $display("Enable = %b | input = %b | output = %b", en, in, out);
        in[2] = 0; in[1] = 1; in[0] = 1; en = 1; #10;
        $display("Enable = %b | input = %b | output = %b", en, in, out);
        in[2] = 1; in[1] = 0; in[0] = 0; en = 1; #10;
        $display("Enable = %b | input = %b | output = %b", en, in, out);
        in[2] = 1; in[1] = 0; in[0] = 1; en = 1; #10;
        $display("Enable = %b | input = %b | output = %b", en, in, out);
        in[2] = 1; in[1] = 1; in[0] = 0; en = 1; #10;
        $display("Enable = %b | input = %b | output = %b", en, in, out);
        in[2] = 1; in[1] = 1; in[0] = 1; en = 1; #10;
        $display("Enable = %b | input = %b | output = %b", en, in, out);
        $finish;
    end
endmodule

decoder3x8waveform.vcd
$date
	Wed Jul 02 02:33:06 2025
$end
$version
	Icarus Verilog
$end
$timescale
	1ps
$end
$scope module tb_Decoder3x8 $end
$var wire 8 ! out [7:0] $end
$var reg 1 " en $end
$var reg 3 # in [2:0] $end
$scope module uut $end
$var wire 1 " en $end
$var wire 3 $ in [2:0] $end
$var reg 8 % out [7:0] $end
$upscope $end
$upscope $end
$enddefinitions $end
$comment Show the parameter values. $end
$dumpall
$end
#0
$dumpvars
b0 %
b0 $
b0 #
0"
b0 !
$end
#10000
b1 !
b1 %
1"
#20000
b10 !
b10 %
b1 #
b1 $
#30000
b100 !
b100 %
b10 #
b10 $
#40000
b1000 !
b1000 %
b11 #
b11 $
#50000
b10000 !
b10000 %
b100 #
b100 $
#60000
b100000 !
b100000 %
b101 #
b101 $
#70000
b1000000 !
b1000000 %
b110 #
b110 $
#80000
b10000000 !
b10000000 %
b111 #
b111 $
