FlipFlops/async_dff.v
//Name: Asynchronous D Flip-Flop
//Date created: 08-07-2025

//This design is asynchronous which means that the reset or set is in no way dependent on the clock, they both work asynchronously.
module async_dff(
    input d, reset, clk, set,
    output reg q_out = 1'b0,
    output qcomp_out
    );
    assign qcomp_out = ~q_out;
    always @(posedge clk or posedge reset or posedge set)begin
       if (reset)begin //Example of active low reset. For active high reset use (reset).
        q_out <= 1'b0;
       end
       else if (set)begin
        q_out <= 1'b1;
       end
       else begin
        q_out <= d;
       end
    end

endmodule

FlipFlops/tb_d_ff.v
`timescale 1ns/1ps

module tb_d_ff;
    reg d;
    reg clk;
    reg reset;
    reg set;
    wire q_out;
    wire qcomp_out;

    async_dff uut(
        .d(d),
        .clk(clk),
        .reset(reset),
        .set(set),
        .q_out(q_out),
        .qcomp_out(qcomp_out)
    );

    initial begin
        reset = 0; set = 0; d = 0; #1;
    end

    always #5 clk = ~clk;

    initial begin
        $dumpfile("dffwaveform.vcd");
        $dumpvars(0, tb_d_ff);
        clk = 1'b0;

        reset = 0; set = 0; d = 1; #50;

        reset = 1;#50;
        reset = 0;#50;

        set = 1;#50;
        set = 0;#50;

        d = 1;#1;
        d = 0;#1;

        set = 1; reset = 1; #50;

        set = 0; reset = 0; #50;

        $finish;
    end
endmodule

dffwaveform.vcd
$date
	Wed Jul 09 14:07:12 2025
$end
$version
	Icarus Verilog
$end
$timescale
	1ps
$end
$scope module tb_d_ff $end
$var wire 1 ! qcomp_out $end
$var wire 1 " q_out $end
$var reg 1 # clk $end
$var reg 1 $ d $end
$var reg 1 % reset $end
$var reg 1 & set $end
$scope module uut $end
$var wire 1 # clk $end
$var wire 1 $ d $end
$var wire 1 ! qcomp_out $end
$var wire 1 % reset $end
$var wire 1 & set $end
$var reg 1 " q_out $end
$upscope $end
$upscope $end
$enddefinitions $end
$comment Show the parameter values. $end
$dumpall
$end
#0
$dumpvars
0&
0%
1$
0#
0"
1!
$end
#5000
0!
1"
1#
#10000
0#
#15000
1#
#20000
0#
#25000
1#
#30000
0#
#35000
1#
#40000
0#
#45000
1#
#50000
1!
0"
0#
1%
#55000
1#
#60000
0#
#65000
1#
#70000
0#
#75000
1#
#80000
0#
#85000
1#
#90000
0#
#95000
1#
#100000
0#
0%
#105000
0!
1"
1#
#110000
0#
#115000
1#
#120000
0#
#125000
1#
#130000
0#
#135000
1#
#140000
0#
#145000
1#
#150000
0#
1&
#155000
1#
#160000
0#
#165000
1#
#170000
0#
#175000
1#
#180000
0#
#185000
1#
#190000
0#
#195000
1#
#200000
0#
0&
#205000
1#
#210000
0#
#215000
1#
#220000
0#
#225000
1#
#230000
0#
#235000
1#
#240000
0#
#245000
1#
#250000
0#
#251000
0$
#252000
1!
0"
1%
1&
#255000
1#
#260000
0#
#265000
1#
#270000
0#
#275000
1#
#280000
0#
#285000
1#
#290000
0#
#295000
1#
#300000
0#
#302000
0%
0&
