RCA/fullsubtractor.v
module fullsubtractor(
    input in0, in1, bin,
    output sub, bout
    );

    assign sub = in0 ^ in1 ^ bin;
    assign bout = (~in0 & in1) | (in1 & bin) | (~in0 & bin);

endmodule

RCA/tb_fullsubtractor.v
`timescale 1ns/1ps

module tb_fullsubtractor();

    reg in0; 
    reg in1;
    reg bin;
    wire bout;
    wire sub;

    fullsubtractor uut (
        .in0(in0),
        .in1(in1),
        .bin(bin),
        .bout(bout),
        .sub(sub)
    );

    initial begin
        $dumpfile("fullsubtractorwaveform.vcd");
        $dumpvars(0, tb_fullsubtractor);

        in0 = 0; in1 = 0; bin = 0; #10;
        $display("input 1 = %b input 2 = %b bin = %b | sub = %b | bout = %b", in0, in1, bin, sub, bout);
        in0 = 0; in1 = 0; bin = 1; #10;
        $display("input 1 = %b input 2 = %b bin = %b | sub = %b | bout = %b", in0, in1, bin, sub, bout);
        in0 = 0; in1 = 1; bin = 0; #10;
        $display("input 1 = %b input 2 = %b bin = %b | sub = %b | bout = %b", in0, in1, bin, sub, bout);
        in0 = 0; in1 = 1; bin = 1; #10;
        $display("input 1 = %b input 2 = %b bin = %b | sub = %b | bout = %b", in0, in1, bin, sub, bout);
        in0 = 1; in1 = 0; bin = 0; #10;
        $display("input 1 = %b input 2 = %b bin = %b | sub = %b | bout = %b", in0, in1, bin, sub, bout);
        in0 = 1; in1 = 0; bin = 1; #10;
        $display("input 1 = %b input 2 = %b bin = %b | sub = %b | bout = %b", in0, in1, bin, sub, bout);
        in0 = 1; in1 = 1; bin = 0; #10;
        $display("input 1 = %b input 2 = %b bin = %b | sub = %b | bout = %b", in0, in1, bin, sub, bout);
        in0 = 1; in1 = 1; bin = 1; #10;
        $display("input 1 = %b input 2 = %b bin = %b | sub = %b | bout = %b", in0, in1, bin, sub, bout);

        $finish;
    end
endmodule

fullsubtractorwaveform.vcd
$date
	Thu Jul 17 23:48:16 2025
$end
$version
	Icarus Verilog
$end
$timescale
	1ps
$end
$scope module tb_fullsubtractor $end
$var wire 1 ! sub $end
$var wire 1 " bout $end
$var reg 1 # bin $end
$var reg 1 $ in0 $end
$var reg 1 % in1 $end
$scope module uut $end
$var wire 1 # bin $end
$var wire 1 " bout $end
$var wire 1 $ in0 $end
$var wire 1 % in1 $end
$var wire 1 ! sub $end
$upscope $end
$upscope $end
$enddefinitions $end
$comment Show the parameter values. $end
$dumpall
$end
#0
$dumpvars
0%
0$
0#
0"
0!
$end
#10000
1"
1!
1#
#20000
0#
1%
#30000
0!
1#
#40000
0"
1!
0#
0%
1$
#50000
0!
1#
#60000
0#
1%
#70000
1"
1!
1#
