RCA/halfadder.v
module halfadder(
    input in0, in1, cin,
    output sum, cout
    );

    assign sum = in0 ^ in1 ^ cin;
    assign cout = in0 & in1 | in0 & cin | in1 & cin;

endmodule

RCA/tb_halfadder.v
`timescale 1ns/1ps

module tb_halfadder();

    reg in0, in1, cin;
    wire sum, cout;

    halfadder uut (
        .in0(in0),
        .in1(in1),
        .cin(cin),
        .cout(cout),
        .sum(sum)
    );

    initial begin
        $dumpfile("halfadderwaveform.vcd");
        $dumpvars(0, tb_halfadder);

        in0 = 0; in1 = 0; cin = 0; #10
        $display("cin = %b input 1 = %b input 2 = %b | sum = %b | cout = %b", cin, in0, in1, sum, cout);
        in0 = 0; in1 = 0; cin = 1; #10
        $display("cin = %b input 1 = %b input 2 = %b | sum = %b | cout = %b", cin, in0, in1, sum, cout);
        in0 = 0; in1 = 1; cin = 0; #10
        $display("cin = %b input 1 = %b input 2 = %b | sum = %b | cout = %b", cin, in0, in1, sum, cout);
        in0 = 0; in1 = 1; cin = 1; #10
        $display("cin = %b input 1 = %b input 2 = %b | sum = %b | cout = %b", cin, in0, in1, sum, cout);
        in0 = 1; in1 = 0; cin = 0; #10
        $display("cin = %b input 1 = %b input 2 = %b | sum = %b | cout = %b", cin, in0, in1, sum, cout);
        in0 = 1; in1 = 0; cin = 1; #10
        $display("cin = %b input 1 = %b input 2 = %b | sum = %b | cout = %b", cin, in0, in1, sum, cout);
        in0 = 1; in1 = 1; cin = 0; #10
        $display("cin = %b input 1 = %b input 2 = %b | sum = %b | cout = %b", cin, in0, in1, sum, cout);
        in0 = 1; in1 = 1; cin = 1; #10
        $display("cin = %b input 1 = %b input 2 = %b | sum = %b | cout = %b", cin, in0, in1, sum, cout);

        $finish;
    end

endmodule

halfadderwaveform.vcd
$date
	Thu Jul 17 23:05:39 2025
$end
$version
	Icarus Verilog
$end
$timescale
	1ps
$end
$scope module tb_halfadder $end
$var wire 1 ! sum $end
$var wire 1 " cout $end
$var reg 1 # cin $end
$var reg 1 $ in0 $end
$var reg 1 % in1 $end
$scope module uut $end
$var wire 1 # cin $end
$var wire 1 " cout $end
$var wire 1 $ in0 $end
$var wire 1 % in1 $end
$var wire 1 ! sum $end
$upscope $end
$upscope $end
$enddefinitions $end
$comment Show the parameter values. $end
$dumpall
$end
#0
$dumpvars
0%
0$
0#
0"
0!
$end
#10000
1!
1#
#20000
0#
1%
#30000
1"
0!
1#
#40000
0"
1!
0#
0%
1$
#50000
1"
0!
1#
#60000
0#
1%
#70000
1!
1#
